{
  "domain": "cloudlink.ae",
  "company_name": "Trusted IT Solution Partner UAE, Cloudlink Solutions",
  "logo": "https://www.google.com/s2/favicons?sz=128&domain=cloudlink.ae",
  "short_description": "We can assist your company in maximising the advantages of automation and a software-defined data centre (SDDC) by providing services using a business-aligned catalogue model.",
  "long_description": "We can assist your company in maximising the advantages of automation and a software-defined data centre (SDDC) by providing services using a business-aligned catalogue model. IT Infrastructure Support We offer expert L1-L3 support for your IT infrastructure or a portion of it. We provide continuous support to your team as a part of our IT infrastructure services.",
  "sector": "Technology",
  "industry": "IT Services",
  "sub_industry": "IT Services",
  "sic_code": "7371",
  "sic_text": "Computer Programming Services",
  "tags": "Technology, IT Services"
}