{
  "domain": "computenordic.com",
  "company_name": "Compute Nordic",
  "logo": "https://www.google.com/s2/favicons?sz=128&domain=computenordic.com",
  "short_description": "Our services 100% renewable hydropower With a focus on corporate sustainability and CO 2 emissions, expand your data centre footprint in Norway and reduce your carbon footprint globally.",
  "long_description": "Our services 100% renewable hydropower With a focus on corporate sustainability and CO 2 emissions, expand your data centre footprint in Norway and reduce your carbon footprint globally.",
  "sector": "Technology",
  "industry": "Software",
  "sub_industry": "Software",
  "sic_code": "7372",
  "sic_text": "Prepackaged Software",
  "tags": "Technology, Software"
}