{
  "domain": "csc2.co.uk",
  "company_name": "CSC2",
  "logo": "https://www.google.com/s2/favicons?sz=128&domain=csc2.co.uk",
  "short_description": "Finding Balance in a Digital World 12 May 2025 Let’s be honest — we rely on technology more than ever.",
  "long_description": "Finding Balance in a Digital World 12 May 2025 Let’s be honest — we rely on technology more than ever. Helping you achieve ISO certification and cyber resilience — with expert advice, zero jargon, and real-world insight. Award-Winning Expertise With 18 years in the industry, Chris was recognised as Freelancer of the Year and Blogger of the Year in 2024.",
  "sector": "Technology",
  "industry": "Cybersecurity",
  "sub_industry": "Cybersecurity",
  "sic_code": "7373",
  "sic_text": "Computer Integrated Systems Design",
  "tags": "Technology, Cybersecurity"
}